CS303-LAB4/matrixops.v
module matrixops (
  input            clk,
  input            rst,
  input            enter,
  input      [1:0] X,
  input      [1:0] Y,
  output reg       Z
);

/* Your design goes here. */

parameter HOLD  = 3'b000;
parameter SET = 3'b001;
parameter CHECK = 3'b010;

reg [15:0] matrix_data;   
reg [2:0] current_state;  
reg [2:0] input_count;    
reg temp_result;         

always @(posedge clk) begin
    
    if (rst) begin
        current_state <= HOLD;
        matrix_data <= 16'b0;
        Z <= 1'b0;
        temp_result <= 1'b0;
        input_count <= 3'b0;

    end else begin
        case (current_state)

            SET: begin
                if (enter && input_count < 5) begin
                    matrix_data[{Y, X}] <= 1'b1;  
                    input_count <= input_count + 1;
                    if (input_count == 4) begin
                        current_state <= CHECK;  
                    end
                end
            end
            
            CHECK: begin
                if (enter) begin
                    temp_result <= matrix_data[{Y, X}];
                    Z <= temp_result;
                end else begin
                    Z <= temp_result;  
                end
            end

            HOLD: begin
                if (enter) begin
                    current_state <= SET;
                    input_count <= 3'b0;
                end
            end

            default: begin
                current_state <= HOLD;  
            end
        endcase
    end
end

endmodule

CS303-LAB4/matrixops_tb.v
module matrixops_tb ();

  //Ports
  reg        clk  ;
  reg        rst  ;
  reg        enter;
  reg  [1:0] X    ;
  reg  [1:0] Y    ;
  wire       Z    ;

  matrixops dut (
    .clk  (clk  ),
    .rst  (rst  ),
    .enter(enter),
    .X    (X    ),
    .Y    (Y    ),
    .Z    (Z    )
  );

  // Half period of our clock signal
  parameter HP = 5;
  // Full period of our clock signal
  parameter FP = (2*HP);

  // For generating the clock signal
  always #HP clk = ~clk;

  initial begin
    //  * Our waveform is saved under this file.
    $dumpfile("matrixops_tb.vcd");

    // * Get the variables from the module.
    $dumpvars(0,matrixops_tb);

    $display("Simulation started.");


  /* 
  // Test Case 0
    clk = 1;
    rst = 1;
    X = 0;
    Y = 0;
    enter = 0;
    #(FP-1); // To avoid race conditions, modify inputs prior to the clock edge

    rst = 0;
    X = 0;
    Y = 0;
    enter = 1;
    #FP;

    rst = 0;
    X = 0;
    Y = 0;
    enter = 0;
    #FP;

    rst = 0;
    X = 2;
    Y = 0;
    enter = 1;
    #FP;

    rst = 0;
    X = 1;
    Y = 1;
    enter = 1;
    #FP;

    rst = 0;
    X = 1;
    Y = 3;
    enter = 1;
    #FP;
    
    rst = 0;
    X = 3;
    Y = 3;
    enter = 1;
    #FP;
    
    rst = 0;
    X = 0;
    Y = 2;
    enter = 1;
    #FP;

    rst = 0;
    X = 1;
    Y = 1;
    enter = 1;
    #FP;
    
    rst = 0;
    X = 1;
    Y = 1;
    enter = 0;
    #FP;
    #FP;

    rst = 0;
    X = 0;
    Y = 0;
    enter = 0;
    #FP;
    #FP;

    rst = 0;
    X = 0;
    Y = 0;
    enter = 1;
    #FP;

    rst = 0;
    X = 1;
    Y = 2;
    enter = 1;
    #FP;

    rst = 0;
    X = 1;
    Y = 2;
    enter = 0;
    #FP;
  */

  /*
    // Test Case 1
    clk = 1;
    rst = 1;
    X = 0;
    Y = 0;
    enter = 0;
    #(FP-1); // To avoid race conditions, modify inputs prior to the clock edge

    rst = 0;
    X = 0;
    Y = 0;
    enter = 1;
    #FP;

    rst = 0;
    X = 0;
    Y = 0;
    enter = 0;
    #FP;

    rst = 0;
    X = 2;
    Y = 0;
    enter = 1;
    #FP;
    #FP;

    rst = 0;
    X = 1;
    Y = 1;
    enter = 1;
    #FP;
    #FP;
    
    rst = 0;
    X = 2;
    Y = 0;
    enter = 1;
    #FP;

    rst = 0;
    X = 1;
    Y = 1;
    enter = 1;
    #FP;
    
    rst = 0;
    X = 1;
    Y = 1;
    enter = 0;
    #FP;

    rst = 0;
    X = 0;
    Y = 0;
    enter = 0;
    #FP;
    #FP;

    rst = 0;
    X = 0;
    Y = 0;
    enter = 1;
    #FP;

    rst = 0;
    X = 2;
    Y = 0;
    enter = 1;
    #FP;

    rst = 0;
    X = 2;
    Y = 0;
    enter = 0;
    #FP;
  */
  
  /*
    // Test Case 2
    clk = 1;
    rst = 1;
    X = 0;
    Y = 0;
    enter = 0;
    #(FP-1); // To avoid race conditions, modify inputs prior to the clock edge

    rst = 0;
    X = 0;
    Y = 0;
    enter = 1;
    #FP;

    rst = 0;
    X = 0;
    Y = 0;
    enter = 0;
    #FP;

    rst = 0;
    X = 0;
    Y = 1;
    enter = 1;
    #FP;

    rst = 0;
    X = 2;
    Y = 3;
    enter = 1;
    #FP;

    rst = 0;
    X = 3;
    Y = 2;
    enter = 1;
    #FP;
    
    rst = 0;
    X = 1;
    Y = 0;
    enter = 1;
    #FP;
    
    rst = 0;
    X = 0;
    Y = 0;
    enter = 1;
    #FP;

    rst = 0;
    X = 1;
    Y = 1;
    enter = 1;
    #FP;
    
    rst = 0;
    X = 1;
    Y = 1;
    enter = 0;
    #FP;
    #FP;

    rst = 0;
    X = 0;
    Y = 0;
    enter = 0;
    #FP;

    rst = 0;
    X = 0;
    Y = 0;
    enter = 1;
    #FP;

    rst = 0;
    X = 2;
    Y = 0;
    enter = 1;
    #FP;

    rst = 0;
    X = 2;
    Y = 0;
    enter = 0;
    #FP;
  */
  
  /*
  // Test Case 3
    clk = 1;
    rst = 1;
    X = 0;
    Y = 0;
    enter = 0;
    #(FP-1); // To avoid race conditions, modify inputs prior to the clock edge

    rst = 0;
    X = 0;
    Y = 0;
    enter = 1;
    #FP;

    rst = 0;
    X = 0;
    Y = 0;
    enter = 0;
    #FP;

    rst = 0;
    X = 0;
    Y = 1;
    enter = 1;
    #FP;

    rst = 0;
    X = 2;
    Y = 3;
    enter = 1;
    #FP;

    rst = 0;
    X = 3;
    Y = 2;
    enter = 1;
    #FP;
    
    rst = 0;
    X = 1;
    Y = 0;
    enter = 1;
    #FP;
    
    rst = 0;
    X = 0;
    Y = 0;
    enter = 1;
    #FP;

    rst = 0;
    X = 1;
    Y = 1;
    enter = 1;
    #FP;
    
    rst = 0;
    X = 1;
    Y = 1;
    enter = 0;
    #FP;
    #FP;

    rst = 1;
    X = 0;
    Y = 0;
    enter = 0;
    #FP;

    rst = 0;
    X = 0;
    Y = 0;
    enter = 1;
    #FP;

    rst = 0;
    X = 2;
    Y = 0;
    enter = 1;
    #FP;

    rst = 0;
    X = 2;
    Y = 0;
    enter = 0;
    #FP;
    */

    /*
    // Test Case 4
    clk = 1;
    rst = 1;
    X = 0;
    Y = 0;
    enter = 0;
    #(FP-1); // To avoid race conditions, modify inputs prior to the clock edge

    rst = 0;
    X = 0;
    Y = 0;
    enter = 1;
    #FP;
    #FP;

    rst = 0;
    X = 0;
    Y = 1;
    enter = 1;
    #FP;

    rst = 0;
    X = 2;
    Y = 3;
    enter = 1;
    #FP;

    rst = 0;
    X = 3;
    Y = 2;
    enter = 1;
    #FP;
    
    rst = 0;
    X = 1;
    Y = 0;
    enter = 1;
    #FP;
    
    rst = 0;
    X = 2;
    Y = 2;
    enter = 1;
    #FP;

    rst = 0;
    X = 1;
    Y = 1;
    enter = 1;
    #FP;

    rst = 0;
    X = 1;
    Y = 1;
    enter = 0;
    #FP;
    #FP;

    rst = 0;
    X = 0;
    Y = 0;
    enter = 0;
    #FP;

    rst = 0;
    X = 0;
    Y = 0;
    enter = 1;
    #FP;

    rst = 0;
    X = 2;
    Y = 0;
    enter = 1;
    #FP;
    
    rst = 0;
    X = 2;
    Y = 0;
    enter = 0;
    #FP;
  */ 
  
  
    // Test Case 5
    clk = 1;
    rst = 1;
    X = 0;
    Y = 0;
    enter = 0;
    #(FP-1); // To avoid race conditions, modify inputs prior to the clock edge

    rst = 0;
    X = 0;
    Y = 0;
    enter = 1;
    #FP;
    #FP;

    rst = 0;
    X = 0;
    Y = 1;
    enter = 1;
    #FP;

    rst = 0;
    X = 2;
    Y = 3;
    enter = 1;
    #FP;

    rst = 0;
    X = 1;
    Y = 1;
    enter = 0;
    #FP;
    
    rst = 0;
    X = 3;
    Y = 2;
    enter = 1;
    #FP;
    
    rst = 0;
    X = 1;
    Y = 0;
    enter = 1;
    #FP;

    rst = 0;
    X = 2;
    Y = 2;
    enter = 1;
    #FP;

    rst = 0;
    X = 1;
    Y = 1;
    enter = 1;
    #FP;

    rst = 0;
    X = 1;
    Y = 1;
    enter = 0;
    #FP;
    #FP;

    rst = 0;
    X = 0;
    Y = 0;
    enter = 0;
    #FP;

    rst = 0;
    X = 0;
    Y = 0;
    enter = 1;
    #FP;
    
    rst = 0;
    X = 2;
    Y = 0;
    enter = 1;
    #FP;

    rst = 0;
    X = 2;
    Y = 0;
    enter = 0;
    #FP;
    
  
    $display("Simulation finished.");
    $finish(); // Finish simulation.
  end

endmodule

CS303-LAB4/matrixops_tb.vcd
$date
	Mon Dec  9 23:29:56 2024
$end
$version
	Icarus Verilog
$end
$timescale
	1s
$end
$scope module matrixops_tb $end
$var wire 1 ! Z $end
$var parameter 64 " FP $end
$var parameter 32 # HP $end
$var reg 2 $ X [1:0] $end
$var reg 2 % Y [1:0] $end
$var reg 1 & clk $end
$var reg 1 ' enter $end
$var reg 1 ( rst $end
$scope module dut $end
$var wire 2 ) X [1:0] $end
$var wire 2 * Y [1:0] $end
$var wire 1 & clk $end
$var wire 1 ' enter $end
$var wire 1 ( rst $end
$var parameter 3 + CHECK $end
$var parameter 3 , HOLD $end
$var parameter 3 - SET $end
$var reg 1 ! Z $end
$var reg 3 . current_state [2:0] $end
$var reg 3 / input_count [2:0] $end
$var reg 16 0 matrix_data [15:0] $end
$var reg 1 1 temp_result $end
$upscope $end
$upscope $end
$enddefinitions $end
$comment Show the parameter values. $end
$dumpall
b1 -
b0 ,
b10 +
b101 #
b1010 "
$end
#0
$dumpvars
01
b0 0
b0 /
b0 .
b0 *
b0 )
1(
0'
1&
b0 %
b0 $
0!
$end
#5
0&
#9
1'
0(
#10
b1 .
1&
#15
0&
#20
b1 /
b1 0
1&
#25
0&
#29
b1 %
b1 *
#30
b10 /
b10001 0
1&
#35
0&
#39
b11 %
b11 *
b10 $
b10 )
#40
b11 /
b100000000010001 0
1&
#45
0&
#49
0'
b1 %
b1 *
b1 $
b1 )
#50
1&
#55
0&
#59
1'
b10 %
b10 *
b11 $
b11 )
#60
b100 /
b100100000010001 0
1&
#65
0&
#69
b0 %
b0 *
b1 $
b1 )
#70
b10 .
b101 /
b100100000010011 0
1&
#75
0&
#79
b10 %
b10 *
b10 $
b10 )
#80
1&
#85
0&
#89
b1 %
b1 *
b1 $
b1 )
#90
1&
#95
0&
#99
0'
#100
1&
#105
0&
#110
1&
#115
0&
#119
b0 %
b0 *
b0 $
b0 )
#120
1&
#125
0&
#129
1'
#130
11
1&
#135
0&
#139
b10 $
b10 )
#140
1!
01
1&
#145
0&
#149
0'
#150
0!
1&
